{
  "cid": 4,
  "lastposttime": 1623704525933,
  "mainPid": 546,
  "postcount": 2,
  "slug": "127/datumformat-p친-forumets-profilsida",
  "tid": 127,
  "timestamp": 1623582809968,
  "title": "Datumformat p친 forumets profilsida...",
  "uid": 198,
  "viewcount": 469,
  "postercount": 2,
  "downvotes": 0,
  "upvotes": 2,
  "teaserPid": 550,
  "tags": [
    {
      "value": "datumformat",
      "valueEscaped": "datumformat",
      "valueEncoded": "datumformat",
      "class": "datumformat"
    },
    {
      "value": "foruminst칛llningar",
      "valueEscaped": "foruminst칛llningar",
      "valueEncoded": "foruminst%C3%A4llningar",
      "class": "foruminst칛llningar"
    },
    {
      "value": "iso",
      "valueEscaped": "iso",
      "valueEncoded": "iso",
      "class": "iso"
    },
    {
      "value": "dataportal.se",
      "valueEscaped": "dataportal.se",
      "valueEncoded": "dataportal.se",
      "class": "dataportal.se"
    }
  ],
  "deleted": 0,
  "locked": 0,
  "pinned": 0,
  "pinExpiry": 0,
  "deleterUid": 0,
  "titleRaw": "Datumformat p친 forumets profilsida...",
  "timestampISO": "2021-06-13T11:13:29.968Z",
  "scheduled": false,
  "lastposttimeISO": "2021-06-14T21:02:05.933Z",
  "pinExpiryISO": "",
  "votes": 2,
  "thumbs": [],
  "posts": [
    {
      "content": "<p dir=\"auto\">Kul att detta forum 칛r uppe och lever. Heja!</p>\n<p dir=\"auto\">Jag 칛r sent till matchen h칛r, men t칛nkte smygstarta med en <strong>liten</strong> reflektion 칬ver <strong>liten</strong> detalj <img src=\"https://community.dataportal.se/assets/plugins/nodebb-plugin-emoji/emoji/android/1f609.png?v=ri45v5qda1g\" class=\"not-responsive emoji emoji-android emoji--wink\" style=\"height:23px;width:auto;vertical-align:middle\" title=\";)\" alt=\"游땔\" /></p>\n<p dir=\"auto\">N칛r jag redigerade min profilsida hickade jag till n칛r jag s친g datumformatet. 츿ven om det inte 칛r en glasklar linje mellan 칬ppna data och etablerade standards, finns det 칛nd친 en po칛ng att g칬ra.  Vi har en utm칛rkt standard i <a href=\"https://sv.wikipedia.org/wiki/ISO_8601\" rel=\"nofollow ugc\">ISO 8601</a> som beskriver exakt hur datum ska formateras. Borde vara en enkel inst칛llning i nodeBB.  Rock on!</p>\n<p dir=\"auto\"><img src=\"/assets/uploads/files/1623582526428-screenshot-2021-06-13-at-11.30.08.png\" alt=\"Screenshot 2021-06-13 at 11.30.08.png\" class=\" img-fluid img-markdown\" /></p>\n",
      "pid": 546,
      "tid": 127,
      "timestamp": 1623582809968,
      "uid": 198,
      "downvotes": 0,
      "upvotes": 2,
      "edited": 1623704681750,
      "editor": {
        "uid": 7,
        "username": "Kristine_",
        "userslug": "kristine_",
        "displayname": "Kristine_"
      },
      "deleted": 0,
      "deleterUid": 0,
      "replies": {
        "hasMore": false,
        "hasSingleImmediateReply": false,
        "users": [],
        "text": "[[topic:one_reply_to_this_post]]",
        "count": 0
      },
      "bookmarks": 0,
      "votes": 2,
      "timestampISO": "2021-06-13T11:13:29.968Z",
      "editedISO": "2021-06-14T21:04:41.750Z",
      "index": 0,
      "user": {
        "uid": 198,
        "username": "jardenberg",
        "fullname": "Joakim Jardenberg",
        "userslug": "jardenberg",
        "reputation": 2,
        "postcount": 1,
        "topiccount": 1,
        "picture": "/assets/uploads/profile/198-profileavatar-1623576540293.jpeg",
        "signature": "<p dir=\"auto\"><a href=\"mailto:joakim@jardenberg.com\" rel=\"nofollow ugc\">joakim@jardenberg.com</a> | <a href=\"https://jardenberg.se\" rel=\"nofollow ugc\">https://jardenberg.se</a> | +46735187700</p>\n<p dir=\"auto\">\"Those who say that it can not be done<br />\nshould get out of the way of those who are doing it!\"</p>\n",
        "banned": false,
        "banned:expire": 0,
        "status": "offline",
        "lastonline": 1623589301856,
        "groupTitle": "[\"\"]",
        "mutedUntil": 0,
        "displayname": "jardenberg",
        "groupTitleArray": [
          ""
        ],
        "icon:text": "J",
        "icon:bgColor": "#33691e",
        "lastonlineISO": "2021-06-13T13:01:41.856Z",
        "banned_until": 0,
        "banned_until_readable": "Not Banned",
        "muted": false,
        "selectedGroups": [],
        "custom_profile_info": []
      },
      "bookmarked": false,
      "upvoted": false,
      "downvoted": false,
      "selfPost": false,
      "events": [],
      "topicOwnerPost": true,
      "display_edit_tools": false,
      "display_delete_tools": false,
      "display_moderator_tools": false,
      "display_move_tools": false,
      "display_post_menu": true
    },
    {
      "content": "<p dir=\"auto\"><a class=\"plugin-mentions-user plugin-mentions-a\" href=\"https://community.dataportal.se/uid/198\">@jardenberg</a><br />\nKul att du hittat hit! Observant reflektion men dessv칛rre s친 kan jag inte se att datumformatet g친r att 칛ndra i inst칛llningarna.</p>\n<p dir=\"auto\">Vi kan se 칬ver om det finns l칛ge att i framtiden 칛ndra det i m친n av tid.</p>\n<p dir=\"auto\">V칛nliga h칛lsningar,<br />\nKristine</p>\n",
      "pid": 550,
      "tid": 127,
      "timestamp": 1623704525933,
      "uid": 7,
      "edited": 1623827528445,
      "editor": {
        "uid": 7,
        "username": "Kristine_",
        "userslug": "kristine_",
        "displayname": "Kristine_"
      },
      "deleted": 0,
      "upvotes": 0,
      "downvotes": 0,
      "deleterUid": 0,
      "replies": {
        "hasMore": false,
        "hasSingleImmediateReply": false,
        "users": [],
        "text": "[[topic:one_reply_to_this_post]]",
        "count": 0
      },
      "bookmarks": 0,
      "votes": 0,
      "timestampISO": "2021-06-14T21:02:05.933Z",
      "editedISO": "2021-06-16T07:12:08.445Z",
      "index": 1,
      "user": {
        "uid": 7,
        "username": "Kristine_",
        "userslug": "kristine_",
        "reputation": 95,
        "postcount": 130,
        "topiccount": 27,
        "picture": "/assets/uploads/profile/7-profileavatar-1612266529992.png",
        "signature": "",
        "banned": false,
        "banned:expire": 0,
        "status": "offline",
        "lastonline": 1699271782573,
        "groupTitle": "[\"\"]",
        "mutedUntil": 0,
        "displayname": "Kristine_",
        "groupTitleArray": [
          ""
        ],
        "icon:text": "K",
        "icon:bgColor": "#795548",
        "lastonlineISO": "2023-11-06T11:56:22.573Z",
        "banned_until": 0,
        "banned_until_readable": "Not Banned",
        "muted": false,
        "selectedGroups": [],
        "custom_profile_info": []
      },
      "bookmarked": false,
      "upvoted": false,
      "downvoted": false,
      "selfPost": false,
      "events": [],
      "topicOwnerPost": false,
      "display_edit_tools": false,
      "display_delete_tools": false,
      "display_moderator_tools": false,
      "display_move_tools": false,
      "display_post_menu": true
    }
  ],
  "events": [],
  "category": {
    "bgColor": "#cd7a6e",
    "cid": 4,
    "class": "col-md-3 col-xs-6",
    "color": "#fff",
    "description": "Om du har synpunkter p친 Sveriges dataportal.",
    "descriptionParsed": "<p dir=\"auto\">Om du har synpunkter p친 Sveriges dataportal.</p>\n",
    "disabled": 0,
    "icon": "fa-question",
    "imageClass": "cover",
    "isSection": 0,
    "link": "",
    "name": "Feedback p친 dataportal.se",
    "numRecentReplies": 1,
    "order": 12,
    "parentCid": 0,
    "post_count": 648,
    "slug": "4/feedback-p친-dataportal-se",
    "topic_count": 103,
    "subCategoriesPerPage": 10,
    "minTags": 0,
    "maxTags": 5,
    "postQueue": 0,
    "totalPostCount": 648,
    "totalTopicCount": 103
  },
  "tagWhitelist": [],
  "minTags": 0,
  "maxTags": 5,
  "thread_tools": [],
  "isFollowing": false,
  "isNotFollowing": true,
  "isIgnoring": false,
  "bookmark": null,
  "postSharing": [
    {
      "id": "facebook",
      "name": "Facebook",
      "class": "fa-facebook",
      "activated": true
    },
    {
      "id": "twitter",
      "name": "Twitter",
      "class": "fa-twitter",
      "activated": true
    }
  ],
  "deleter": null,
  "merger": null,
  "related": [],
  "unreplied": false,
  "icons": [],
  "privileges": {
    "topics:reply": false,
    "topics:read": true,
    "topics:schedule": false,
    "topics:tag": false,
    "topics:delete": false,
    "posts:edit": false,
    "posts:history": false,
    "posts:upvote": false,
    "posts:downvote": false,
    "posts:delete": false,
    "posts:view_deleted": false,
    "read": true,
    "purge": false,
    "view_thread_tools": false,
    "editable": false,
    "deletable": false,
    "view_deleted": false,
    "view_scheduled": false,
    "isAdminOrMod": false,
    "disabled": 0,
    "tid": "127",
    "uid": 0
  },
  "topicStaleDays": 60,
  "reputation:disabled": 0,
  "downvote:disabled": 1,
  "feeds:disableRSS": 0,
  "signatures:hideDuplicates": 0,
  "bookmarkThreshold": 5,
  "necroThreshold": 7,
  "postEditDuration": 300,
  "postDeleteDuration": 0,
  "scrollToMyPost": true,
  "updateUrlWithPostIndex": true,
  "allowMultipleBadges": true,
  "privateUploads": false,
  "showPostPreviewsOnHover": true,
  "rssFeedUrl": "/topic/127.rss",
  "postIndex": 1,
  "breadcrumbs": [
    {
      "text": "[[global:home]]",
      "url": "/"
    },
    {
      "text": "[[global:header.categories]]",
      "url": "/categories"
    },
    {
      "text": "Feedback p친 dataportal.se",
      "url": "/category/4/feedback-p친-dataportal-se",
      "cid": 4
    }
  ],
  "pagination": {
    "prev": {
      "page": 1,
      "active": false
    },
    "next": {
      "page": 1,
      "active": false
    },
    "first": {
      "page": 1,
      "active": true
    },
    "last": {
      "page": 1,
      "active": true
    },
    "rel": [],
    "pages": [],
    "currentPage": 1,
    "pageCount": 1
  },
  "loggedIn": false,
  "loggedInUser": {
    "uid": 0,
    "username": "[[global:guest]]",
    "picture": "",
    "icon:text": "?",
    "icon:bgColor": "#aaa"
  },
  "relative_path": "",
  "template": {
    "name": "topic",
    "topic": true
  },
  "url": "/topic/127",
  "bodyClass": "page-topic page-topic-127 template-topic page-topic-category-4 page-topic-category-feedback-p친-dataportal-se parent-category-4 page-status-200 theme-harmony user-guest",
  "_header": {
    "tags": {
      "meta": [
        {
          "name": "viewport",
          "content": "width&#x3D;device-width, initial-scale&#x3D;1.0"
        },
        {
          "name": "content-type",
          "content": "text/html; charset=UTF-8",
          "noEscape": true
        },
        {
          "name": "apple-mobile-web-app-capable",
          "content": "yes"
        },
        {
          "name": "mobile-web-app-capable",
          "content": "yes"
        },
        {
          "property": "og:site_name",
          "content": "Community p친 Sveriges dataportal"
        },
        {
          "name": "msapplication-badge",
          "content": "frequency=30; polling-uri=https://community.dataportal.se/sitemap.xml",
          "noEscape": true
        },
        {
          "name": "theme-color",
          "content": "#ACB3A8"
        },
        {
          "name": "keywords",
          "content": "칬ppna data,api,open data,innovation,dataportal,community,forum"
        },
        {
          "name": "msapplication-square150x150logo",
          "content": "/assets/uploads/system/site-logo.svg",
          "noEscape": true
        },
        {
          "name": "title",
          "content": "Datumformat p친 forumets profilsida..."
        },
        {
          "name": "description",
          "content": "Kul att detta forum 칛r uppe och lever. Heja! Jag 칛r sent till matchen h칛r, men t칛nkte smygstarta med en liten reflektion 칬ver liten detalj  N칛r jag redigerade min profilsida hickade jag till n칛r jag s친g datumformatet. 츿ven om det inte 칛r en glasklar linje..."
        },
        {
          "property": "og:title",
          "content": "Datumformat p친 forumets profilsida..."
        },
        {
          "property": "og:description",
          "content": "Kul att detta forum 칛r uppe och lever. Heja! Jag 칛r sent till matchen h칛r, men t칛nkte smygstarta med en liten reflektion 칬ver liten detalj  N칛r jag redigerade min profilsida hickade jag till n칛r jag s친g datumformatet. 츿ven om det inte 칛r en glasklar linje..."
        },
        {
          "property": "og:type",
          "content": "article"
        },
        {
          "property": "article:published_time",
          "content": "2021-06-13T11:13:29.968Z"
        },
        {
          "property": "article:modified_time",
          "content": "2021-06-14T21:04:41.750Z"
        },
        {
          "property": "article:section",
          "content": "Feedback p친 dataportal.se"
        },
        {
          "property": "og:image",
          "content": "https://community.dataportal.se/assets/uploads/files/1623582526428-screenshot-2021-06-13-at-11.30.08.png",
          "noEscape": true
        },
        {
          "property": "og:image:url",
          "content": "https://community.dataportal.se/assets/uploads/files/1623582526428-screenshot-2021-06-13-at-11.30.08.png",
          "noEscape": true
        },
        {
          "property": "og:image:width",
          "content": "372"
        },
        {
          "property": "og:image:height",
          "content": "152"
        },
        {
          "property": "og:image",
          "content": "https://community.dataportal.se/assets/uploads/profile/198-profileavatar-1623576540293.jpeg",
          "noEscape": true
        },
        {
          "property": "og:image:url",
          "content": "https://community.dataportal.se/assets/uploads/profile/198-profileavatar-1623576540293.jpeg",
          "noEscape": true
        },
        {
          "property": "og:image",
          "content": "https://community.dataportal.se/assets/uploads/system/og-image.jpg",
          "noEscape": true
        },
        {
          "property": "og:image:url",
          "content": "https://community.dataportal.se/assets/uploads/system/og-image.jpg",
          "noEscape": true
        },
        {
          "property": "og:image:width",
          "content": "1600"
        },
        {
          "property": "og:image:height",
          "content": "555"
        },
        {
          "content": "https://community.dataportal.se/api/topic/127",
          "property": "og:url"
        }
      ],
      "link": [
        {
          "rel": "icon",
          "type": "image/x-icon",
          "href": "/assets/uploads/system/favicon.ico?v&#x3D;ri45v5qda1g"
        },
        {
          "rel": "manifest",
          "href": "/manifest.webmanifest",
          "crossorigin": "use-credentials"
        },
        {
          "rel": "search",
          "type": "application/opensearchdescription+xml",
          "title": "Community p친 Sveriges dataportal",
          "href": "/osd.xml"
        },
        {
          "rel": "apple-touch-icon",
          "href": "/assets/uploads/system/touchicon-orig.png"
        },
        {
          "rel": "icon",
          "sizes": "36x36",
          "href": "/assets/uploads/system/touchicon-36.png"
        },
        {
          "rel": "icon",
          "sizes": "48x48",
          "href": "/assets/uploads/system/touchicon-48.png"
        },
        {
          "rel": "icon",
          "sizes": "72x72",
          "href": "/assets/uploads/system/touchicon-72.png"
        },
        {
          "rel": "icon",
          "sizes": "96x96",
          "href": "/assets/uploads/system/touchicon-96.png"
        },
        {
          "rel": "icon",
          "sizes": "144x144",
          "href": "/assets/uploads/system/touchicon-144.png"
        },
        {
          "rel": "icon",
          "sizes": "192x192",
          "href": "/assets/uploads/system/touchicon-192.png"
        },
        {
          "rel": "prefetch",
          "href": "/assets/src/modules/composer.js?v&#x3D;ri45v5qda1g"
        },
        {
          "rel": "prefetch",
          "href": "/assets/src/modules/composer/uploads.js?v&#x3D;ri45v5qda1g"
        },
        {
          "rel": "prefetch",
          "href": "/assets/src/modules/composer/drafts.js?v&#x3D;ri45v5qda1g"
        },
        {
          "rel": "prefetch",
          "href": "/assets/src/modules/composer/tags.js?v&#x3D;ri45v5qda1g"
        },
        {
          "rel": "prefetch",
          "href": "/assets/src/modules/composer/categoryList.js?v&#x3D;ri45v5qda1g"
        },
        {
          "rel": "prefetch",
          "href": "/assets/src/modules/composer/resize.js?v&#x3D;ri45v5qda1g"
        },
        {
          "rel": "prefetch",
          "href": "/assets/src/modules/composer/autocomplete.js?v&#x3D;ri45v5qda1g"
        },
        {
          "rel": "prefetch",
          "href": "/assets/templates/composer.tpl?v&#x3D;ri45v5qda1g"
        },
        {
          "rel": "prefetch",
          "href": "/assets/language/sv/topic.json?v&#x3D;ri45v5qda1g"
        },
        {
          "rel": "prefetch",
          "href": "/assets/language/sv/modules.json?v&#x3D;ri45v5qda1g"
        },
        {
          "rel": "prefetch",
          "href": "/assets/language/sv/tags.json?v&#x3D;ri45v5qda1g"
        },
        {
          "rel": "prefetch stylesheet",
          "type": "",
          "href": "/assets/plugins/nodebb-plugin-markdown/styles/default.css"
        },
        {
          "rel": "prefetch",
          "href": "/assets/language/sv/markdown.json?v&#x3D;ri45v5qda1g"
        },
        {
          "rel": "stylesheet",
          "href": "https://community.dataportal.se/assets/plugins/nodebb-plugin-emoji/emoji/styles.css?v&#x3D;ri45v5qda1g"
        },
        {
          "rel": "canonical",
          "href": "https://community.dataportal.se/topic/127/datumformat-p친-forumets-profilsida",
          "noEscape": true
        },
        {
          "rel": "alternate",
          "type": "application/rss+xml",
          "href": "/topic/127.rss"
        },
        {
          "rel": "up",
          "href": "https://community.dataportal.se/category/4/feedback-p친-dataportal-se"
        },
        {
          "rel": "author",
          "href": "https://community.dataportal.se/user/jardenberg"
        }
      ]
    }
  },
  "widgets": {
    "footer": [
      {
        "html": "<footer id=\"footer\" class=\"container footer\" style=\"margin-bottom:1em\">\r\n\t<div>\r\n<img src=\"https://community.dataportal.se/assets/uploads/files/finansieras_av_europeiskaunionen.png\" alt=\"Finansieras av Europeiska unionen logo\" width=\"200\" />\r\n\t\t\r\n\t</div>\r\n</footer>"
      }
    ],
    "header": [
      {
        "html": "<h1>Community p친 Sveriges dataportal</h1>"
      }
    ]
  }
}